MANIFEST.in
README.rst
setup.py
src/testunicodepackagedependant.py
src/testunicodepackagedependant.egg-info/PKG-INFO
src/testunicodepackagedependant.egg-info/SOURCES.txt
src/testunicodepackagedependant.egg-info/dependency_links.txt
src/testunicodepackagedependant.egg-info/requires.txt
src/testunicodepackagedependant.egg-info/top_level.txt