Metadata-Version: 1.1
Name: testunicodepackagedependant
Version: 1.0
Summary: Test package dependant on a package with Unicode filenames
Home-page: http://pypi.python.org/pypi/testunicodepackagedependant/
Author: Lukasz Langa
Author-email: lukasz@langa.pl
License: MIT
Platform: Any
Classifier: Development Status :: 4 - Beta
Classifier: Intended Audience :: Other Audience
Classifier: License :: OSI Approved :: MIT License
Classifier: Operating System :: OS Independent
Classifier: Programming Language :: Python :: 2
Classifier: Programming Language :: Python :: 2.6
Classifier: Programming Language :: Python :: 2.7
Classifier: Programming Language :: Python :: 3
Classifier: Programming Language :: Python :: 3.1
Classifier: Programming Language :: Python :: 3.2
Classifier: Programming Language :: Python :: 3.3
Classifier: Programming Language :: Python :: 3.4
